MANIFEST.in
README.md
requirements.txt
setup.py
github/__init__.py
github/com/__init__.py
github/com/envoyproxy/__init__.py
github/com/envoyproxy/protoc_gen_validate/__init__.py
github/com/envoyproxy/protoc_gen_validate/validate/__init__.py
github/com/envoyproxy/protoc_gen_validate/validate/validate_pb2.py
github/com/envoyproxy/protoc_gen_validate/validate/validate_pb2_grpc.py
github/com/mwitkow/__init__.py
github/com/mwitkow/go_proto_validators/__init__.py
github/com/mwitkow/go_proto_validators/validator_pb2.py
github/com/mwitkow/go_proto_validators/validator_pb2_grpc.py
laiye_python_third_proto.egg-info/PKG-INFO
laiye_python_third_proto.egg-info/SOURCES.txt
laiye_python_third_proto.egg-info/dependency_links.txt
laiye_python_third_proto.egg-info/top_level.txt
protoc_gen_swagger/__init__.py
protoc_gen_swagger/options/__init__.py
protoc_gen_swagger/options/annotations_pb2.py
protoc_gen_swagger/options/annotations_pb2_grpc.py
protoc_gen_swagger/options/openapiv2_pb2.py
protoc_gen_swagger/options/openapiv2_pb2_grpc.py