Metadata-Version: 1.0
Name: laiye-python-third-proto
Version: 0.0.1
Summary: Python laiye third proto
Home-page: https://github.com/laiyethirdproto/laiye-python-third-proto.git
Author: Tang Ying
Author-email: tangying@laiye.com
License: MIT
Platform: UNKNOWN
